aida/__init__.py
aida/branching.py
aida/choices.py
aida/core.py
aida/lang.py
aidalib-0.2.dist-info/LICENSE
aidalib-0.2.dist-info/METADATA
aidalib-0.2.dist-info/WHEEL
aidalib-0.2.dist-info/top_level.txt
aidalib-0.2.dist-info/RECORD
