Metadata-Version: 2.1
Name: aidalib
Version: 0.2
Summary: Aida is a language agnostic library for text generation.
Home-page: https://github.com/mediatechlab/aida-lib
Author: Giulio Bottari
Author-email: giuliobottari@gmail.com
License: MIT
Project-URL: Bus Tracker, https://github.com/mediatechlab/aida-lib/issues
Project-URL: Documentation, https://github.com/mediatechlab/aida-lib/blob/master/README.md
Project-URL: Source Code, https://github.com/mediatechlab/aida-lib
Keywords: nlg natural-language-generation text-generation library
Platform: UNKNOWN
Classifier: Programming Language :: Python :: 3
Classifier: Intended Audience :: Developers
